<?xml version="1.0" encoding="utf-8"?>
<Patch>
  <Operation Class="PatchOperationAddModExtension">
    <xpath>Defs/RecipeDef[defName="MakeAmmo_44-40Winchester_FMJ"]</xpath>
    <value>
      <li Class="LifeLessons.BillProficiencyExtension">
        <requirements>
          <li>Smithing</li>
          <li>Labourer</li>
          <li>Chemistry</li>
        </requirements>
        <unqualifiedPenalty>
          <qualityCap>Legendary</qualityCap>
        </unqualifiedPenalty>
        <hardRequirement>False</hardRequirement>
      </li>
    </value>
  </Operation>
  <Operation Class="PatchOperationAddModExtension">
    <xpath>Defs/RecipeDef[defName="MakeAmmo_4570Gov_FMJ"]</xpath>
    <value>
      <li Class="LifeLessons.BillProficiencyExtension">
        <requirements>
          <li>Chemistry</li>
          <li>Smithing</li>
          <li>Labourer</li>
        </requirements>
        <unqualifiedPenalty>
          <qualityCap>Legendary</qualityCap>
        </unqualifiedPenalty>
        <hardRequirement>False</hardRequirement>
      </li>
    </value>
  </Operation>
  <Operation Class="PatchOperationAddModExtension">
    <xpath>Defs/RecipeDef[defName="MakeAmmo_5656Spencer_FMJ"]</xpath>
    <value>
      <li Class="LifeLessons.BillProficiencyExtension">
        <requirements>
          <li>Chemistry</li>
          <li>Smithing</li>
          <li>Labourer</li>
        </requirements>
        <unqualifiedPenalty>
          <qualityCap>Legendary</qualityCap>
        </unqualifiedPenalty>
        <hardRequirement>False</hardRequirement>
      </li>
    </value>
  </Operation>
  <Operation Class="PatchOperationAddModExtension">
    <xpath>Defs/RecipeDef[defName="MakeAmmo_106Caliber_Lead"]</xpath>
    <value>
      <li Class="LifeLessons.BillProficiencyExtension">
        <requirements>
          <li>Smithing</li>
          <li>Labourer</li>
          <li>Chemistry</li>
        </requirements>
        <unqualifiedPenalty>
          <qualityCap>Legendary</qualityCap>
        </unqualifiedPenalty>
        <hardRequirement>False</hardRequirement>
      </li>
    </value>
  </Operation>
  <Operation Class="PatchOperationAddModExtension">
    <xpath>Defs/RecipeDef[defName="MakeAmmo_125Caliber_Lead"]</xpath>
    <value>
      <li Class="LifeLessons.BillProficiencyExtension">
        <requirements>
          <li>Smithing</li>
          <li>Chemistry</li>
          <li>Labourer</li>
        </requirements>
        <unqualifiedPenalty>
          <qualityCap>Legendary</qualityCap>
        </unqualifiedPenalty>
        <hardRequirement>False</hardRequirement>
      </li>
    </value>
  </Operation>
  <Operation Class="PatchOperationAddModExtension">
    <xpath>Defs/RecipeDef[defName="MakeAmmo_1543x54Caliber"]</xpath>
    <value>
      <li Class="LifeLessons.BillProficiencyExtension">
        <requirements>
          <li>Chemistry</li>
          <li>Smithing</li>
          <li>Labourer</li>
        </requirements>
        <unqualifiedPenalty>
          <qualityCap>Legendary</qualityCap>
        </unqualifiedPenalty>
        <hardRequirement>False</hardRequirement>
      </li>
    </value>
  </Operation>
  <Operation Class="PatchOperationAddModExtension">
    <xpath>Defs/RecipeDef[defName="MakeAmmo_33Caliber_Lead"]</xpath>
    <value>
      <li Class="LifeLessons.BillProficiencyExtension">
        <requirements>
          <li>Smithing</li>
          <li>Labourer</li>
          <li>Chemistry</li>
        </requirements>
        <unqualifiedPenalty>
          <qualityCap>Legendary</qualityCap>
        </unqualifiedPenalty>
        <hardRequirement>False</hardRequirement>
      </li>
    </value>
  </Operation>
  <Operation Class="PatchOperationAddModExtension">
    <xpath>Defs/RecipeDef[defName="MakeAmmo_38Volcanic_Lead"]</xpath>
    <value>
      <li Class="LifeLessons.BillProficiencyExtension">
        <requirements>
          <li>Smithing</li>
          <li>Labourer</li>
          <li>Chemistry</li>
        </requirements>
        <unqualifiedPenalty>
          <qualityCap>Legendary</qualityCap>
        </unqualifiedPenalty>
        <hardRequirement>False</hardRequirement>
      </li>
    </value>
  </Operation>
  <Operation Class="PatchOperationAddModExtension">
    <xpath>Defs/RecipeDef[defName="MakeAmmo_4555RCaliber_Lead"]</xpath>
    <value>
      <li Class="LifeLessons.BillProficiencyExtension">
        <requirements>
          <li>Chemistry</li>
          <li>Smithing</li>
          <li>Labourer</li>
        </requirements>
        <unqualifiedPenalty>
          <qualityCap>Legendary</qualityCap>
        </unqualifiedPenalty>
        <hardRequirement>False</hardRequirement>
      </li>
    </value>
  </Operation>
  <Operation Class="PatchOperationAddModExtension">
    <xpath>Defs/RecipeDef[defName="MakeAmmo_45Caliber_Lead"]</xpath>
    <value>
      <li Class="LifeLessons.BillProficiencyExtension">
        <requirements>
          <li>Smithing</li>
          <li>Labourer</li>
          <li>Chemistry</li>
        </requirements>
        <unqualifiedPenalty>
          <qualityCap>Legendary</qualityCap>
        </unqualifiedPenalty>
        <hardRequirement>False</hardRequirement>
      </li>
    </value>
  </Operation>
  <Operation Class="PatchOperationAddModExtension">
    <xpath>Defs/RecipeDef[defName="MakeAmmo_47Caliber_Lead"]</xpath>
    <value>
      <li Class="LifeLessons.BillProficiencyExtension">
        <requirements>
          <li>Chemistry</li>
          <li>Smithing</li>
          <li>Labourer</li>
        </requirements>
        <unqualifiedPenalty>
          <qualityCap>Legendary</qualityCap>
        </unqualifiedPenalty>
        <hardRequirement>False</hardRequirement>
      </li>
    </value>
  </Operation>
  <Operation Class="PatchOperationAddModExtension">
    <xpath>Defs/RecipeDef[defName="MakeAmmo_50Caliber_Lead"]</xpath>
    <value>
      <li Class="LifeLessons.BillProficiencyExtension">
        <requirements>
          <li>Chemistry</li>
          <li>Smithing</li>
          <li>Labourer</li>
        </requirements>
        <unqualifiedPenalty>
          <qualityCap>Legendary</qualityCap>
        </unqualifiedPenalty>
        <hardRequirement>False</hardRequirement>
      </li>
    </value>
  </Operation>
  <Operation Class="PatchOperationAddModExtension">
    <xpath>Defs/RecipeDef[defName="MakeAmmo_50CaliberCap_Lead"]</xpath>
    <value>
      <li Class="LifeLessons.BillProficiencyExtension">
        <requirements>
          <li>Chemistry</li>
          <li>Smithing</li>
          <li>Labourer</li>
        </requirements>
        <unqualifiedPenalty>
          <qualityCap>Legendary</qualityCap>
        </unqualifiedPenalty>
        <hardRequirement>False</hardRequirement>
      </li>
    </value>
  </Operation>
  <Operation Class="PatchOperationAddModExtension">
    <xpath>Defs/RecipeDef[defName="MakeAmmo_52Caliber_Lead"]</xpath>
    <value>
      <li Class="LifeLessons.BillProficiencyExtension">
        <requirements>
          <li>Chemistry</li>
          <li>Smithing</li>
          <li>Labourer</li>
        </requirements>
        <unqualifiedPenalty>
          <qualityCap>Legendary</qualityCap>
        </unqualifiedPenalty>
        <hardRequirement>False</hardRequirement>
      </li>
    </value>
  </Operation>
  <Operation Class="PatchOperationAddModExtension">
    <xpath>Defs/RecipeDef[defName="MakeAmmo_53Caliber_Lead"]</xpath>
    <value>
      <li Class="LifeLessons.BillProficiencyExtension">
        <requirements>
          <li>Chemistry</li>
          <li>Smithing</li>
          <li>Labourer</li>
        </requirements>
        <unqualifiedPenalty>
          <qualityCap>Legendary</qualityCap>
        </unqualifiedPenalty>
        <hardRequirement>False</hardRequirement>
      </li>
    </value>
  </Operation>
  <Operation Class="PatchOperationAddModExtension">
    <xpath>Defs/RecipeDef[defName="MakeAmmo_54Caliber_Lead"]</xpath>
    <value>
      <li Class="LifeLessons.BillProficiencyExtension">
        <requirements>
          <li>Chemistry</li>
          <li>Smithing</li>
          <li>Labourer</li>
        </requirements>
        <unqualifiedPenalty>
          <qualityCap>Legendary</qualityCap>
        </unqualifiedPenalty>
        <hardRequirement>False</hardRequirement>
      </li>
    </value>
  </Operation>
  <Operation Class="PatchOperationAddModExtension">
    <xpath>Defs/RecipeDef[defName="MakeAmmo_55Caliber_Lead"]</xpath>
    <value>
      <li Class="LifeLessons.BillProficiencyExtension">
        <requirements>
          <li>Chemistry</li>
          <li>Smithing</li>
          <li>Labourer</li>
        </requirements>
        <unqualifiedPenalty>
          <qualityCap>Legendary</qualityCap>
        </unqualifiedPenalty>
        <hardRequirement>False</hardRequirement>
      </li>
    </value>
  </Operation>
  <Operation Class="PatchOperationAddModExtension">
    <xpath>Defs/RecipeDef[defName="MakeAmmo_56Caliber_Lead"]</xpath>
    <value>
      <li Class="LifeLessons.BillProficiencyExtension">
        <requirements>
          <li>Chemistry</li>
          <li>Labourer</li>
          <li>Smithing</li>
        </requirements>
        <unqualifiedPenalty>
          <qualityCap>Legendary</qualityCap>
        </unqualifiedPenalty>
        <hardRequirement>False</hardRequirement>
      </li>
    </value>
  </Operation>
  <Operation Class="PatchOperationAddModExtension">
    <xpath>Defs/RecipeDef[defName="MakeAmmo_577CaliberCap_Lead"]</xpath>
    <value>
      <li Class="LifeLessons.BillProficiencyExtension">
        <requirements>
          <li>Chemistry</li>
          <li>Smithing</li>
          <li>Labourer</li>
        </requirements>
        <unqualifiedPenalty>
          <qualityCap>Legendary</qualityCap>
        </unqualifiedPenalty>
        <hardRequirement>False</hardRequirement>
      </li>
    </value>
  </Operation>
  <Operation Class="PatchOperationAddModExtension">
    <xpath>Defs/RecipeDef[defName="MakeAmmo_577CaliberCapMetal_Lead"]</xpath>
    <value>
      <li Class="LifeLessons.BillProficiencyExtension">
        <requirements>
          <li>Chemistry</li>
          <li>Smithing</li>
          <li>Labourer</li>
        </requirements>
        <unqualifiedPenalty>
          <qualityCap>Legendary</qualityCap>
        </unqualifiedPenalty>
        <hardRequirement>False</hardRequirement>
      </li>
    </value>
  </Operation>
  <Operation Class="PatchOperationAddModExtension">
    <xpath>Defs/RecipeDef[defName="MakeAmmo_59Caliber_Lead"]</xpath>
    <value>
      <li Class="LifeLessons.BillProficiencyExtension">
        <requirements>
          <li>Chemistry</li>
          <li>Smithing</li>
          <li>Labourer</li>
        </requirements>
        <unqualifiedPenalty>
          <qualityCap>Legendary</qualityCap>
        </unqualifiedPenalty>
        <hardRequirement>False</hardRequirement>
      </li>
    </value>
  </Operation>
  <Operation Class="PatchOperationAddModExtension">
    <xpath>Defs/RecipeDef[defName="MakeAmmo_60Caliber_Lead"]</xpath>
    <value>
      <li Class="LifeLessons.BillProficiencyExtension">
        <requirements>
          <li>Chemistry</li>
          <li>Smithing</li>
          <li>Labourer</li>
        </requirements>
        <unqualifiedPenalty>
          <qualityCap>Legendary</qualityCap>
        </unqualifiedPenalty>
        <hardRequirement>False</hardRequirement>
      </li>
    </value>
  </Operation>
  <Operation Class="PatchOperationAddModExtension">
    <xpath>Defs/RecipeDef[defName="MakeAmmo_625Caliber_Lead"]</xpath>
    <value>
      <li Class="LifeLessons.BillProficiencyExtension">
        <requirements>
          <li>Chemistry</li>
          <li>Smithing</li>
          <li>Labourer</li>
        </requirements>
        <unqualifiedPenalty>
          <qualityCap>Legendary</qualityCap>
        </unqualifiedPenalty>
        <hardRequirement>False</hardRequirement>
      </li>
    </value>
  </Operation>
  <Operation Class="PatchOperationAddModExtension">
    <xpath>Defs/RecipeDef[defName="MakeAmmo_62Blunderbuss_Buck"]</xpath>
    <value>
      <li Class="LifeLessons.BillProficiencyExtension">
        <requirements>
          <li>Chemistry</li>
          <li>Smithing</li>
          <li>Labourer</li>
        </requirements>
        <unqualifiedPenalty>
          <qualityCap>Legendary</qualityCap>
        </unqualifiedPenalty>
        <hardRequirement>False</hardRequirement>
      </li>
    </value>
  </Operation>
  <Operation Class="PatchOperationAddModExtension">
    <xpath>Defs/RecipeDef[defName="MakeAmmo_62Blunderbuss_Bird"]</xpath>
    <value>
      <li Class="LifeLessons.BillProficiencyExtension">
        <requirements>
          <li>Chemistry</li>
          <li>Smithing</li>
          <li>Labourer</li>
        </requirements>
        <unqualifiedPenalty>
          <qualityCap>Legendary</qualityCap>
        </unqualifiedPenalty>
        <hardRequirement>False</hardRequirement>
      </li>
    </value>
  </Operation>
  <Operation Class="PatchOperationAddModExtension">
    <xpath>Defs/RecipeDef[defName="MakeAmmo_62Caliber_Lead"]</xpath>
    <value>
      <li Class="LifeLessons.BillProficiencyExtension">
        <requirements>
          <li>Chemistry</li>
          <li>Smithing</li>
          <li>Labourer</li>
        </requirements>
        <unqualifiedPenalty>
          <qualityCap>Legendary</qualityCap>
        </unqualifiedPenalty>
        <hardRequirement>False</hardRequirement>
      </li>
    </value>
  </Operation>
  <Operation Class="PatchOperationAddModExtension">
    <xpath>Defs/RecipeDef[defName="MakeAmmo_65Caliber_Lead"]</xpath>
    <value>
      <li Class="LifeLessons.BillProficiencyExtension">
        <requirements>
          <li>Chemistry</li>
          <li>Smithing</li>
          <li>Labourer</li>
        </requirements>
        <unqualifiedPenalty>
          <qualityCap>Legendary</qualityCap>
        </unqualifiedPenalty>
        <hardRequirement>False</hardRequirement>
      </li>
    </value>
  </Operation>
  <Operation Class="PatchOperationAddModExtension">
    <xpath>Defs/RecipeDef[defName="MakeAmmo_69CaliberCap_Lead"]</xpath>
    <value>
      <li Class="LifeLessons.BillProficiencyExtension">
        <requirements>
          <li>Chemistry</li>
          <li>Smithing</li>
          <li>Labourer</li>
        </requirements>
        <unqualifiedPenalty>
          <qualityCap>Legendary</qualityCap>
        </unqualifiedPenalty>
        <hardRequirement>False</hardRequirement>
      </li>
    </value>
  </Operation>
  <Operation Class="PatchOperationAddModExtension">
    <xpath>Defs/RecipeDef[defName="MakeAmmo_70Caliber_Lead"]</xpath>
    <value>
      <li Class="LifeLessons.BillProficiencyExtension">
        <requirements>
          <li>Chemistry</li>
          <li>Smithing</li>
          <li>Labourer</li>
        </requirements>
        <unqualifiedPenalty>
          <qualityCap>Legendary</qualityCap>
        </unqualifiedPenalty>
        <hardRequirement>False</hardRequirement>
      </li>
    </value>
  </Operation>
  <Operation Class="PatchOperationAddModExtension">
    <xpath>Defs/RecipeDef[defName="MakeAmmo_80Caliber_Lead"]</xpath>
    <value>
      <li Class="LifeLessons.BillProficiencyExtension">
        <requirements>
          <li>Chemistry</li>
          <li>Smithing</li>
          <li>Labourer</li>
        </requirements>
        <unqualifiedPenalty>
          <qualityCap>Legendary</qualityCap>
        </unqualifiedPenalty>
        <hardRequirement>False</hardRequirement>
      </li>
    </value>
  </Operation>
  <Operation Class="PatchOperationAddModExtension">
    <xpath>Defs/RecipeDef[defName="MakeAmmo_87Gonne_Lead"]</xpath>
    <value>
      <li Class="LifeLessons.BillProficiencyExtension">
        <requirements>
          <li>Chemistry</li>
          <li>Smithing</li>
          <li>Labourer</li>
        </requirements>
        <unqualifiedPenalty>
          <qualityCap>Legendary</qualityCap>
        </unqualifiedPenalty>
        <hardRequirement>False</hardRequirement>
      </li>
    </value>
  </Operation>
  <Operation Class="PatchOperationAddModExtension">
    <xpath>Defs/RecipeDef[defName="MakeAmmo_87Gonne_Buck"]</xpath>
    <value>
      <li Class="LifeLessons.BillProficiencyExtension">
        <requirements>
          <li>Chemistry</li>
          <li>Smithing</li>
          <li>Labourer</li>
        </requirements>
        <unqualifiedPenalty>
          <qualityCap>Legendary</qualityCap>
        </unqualifiedPenalty>
        <hardRequirement>False</hardRequirement>
      </li>
    </value>
  </Operation>
  <Operation Class="PatchOperationAddModExtension">
    <xpath>Defs/RecipeDef[defName="MakeAmmo_87Gonne_Emp"]</xpath>
    <value>
      <li Class="LifeLessons.BillProficiencyExtension">
        <requirements>
          <li>Chemistry</li>
          <li>Smithing</li>
          <li>Labourer</li>
          <li>BasicScience</li>
        </requirements>
        <unqualifiedPenalty>
          <qualityCap>Legendary</qualityCap>
        </unqualifiedPenalty>
        <hardRequirement>False</hardRequirement>
      </li>
    </value>
  </Operation>
  <Operation Class="PatchOperationAddModExtension">
    <xpath>Defs/RecipeDef[defName="MakeAmmo_87Gonne_Bolt"]</xpath>
    <value>
      <li Class="LifeLessons.BillProficiencyExtension">
        <requirements>
          <li>Chemistry</li>
          <li>Smithing</li>
          <li>Labourer</li>
        </requirements>
        <unqualifiedPenalty>
          <qualityCap>Legendary</qualityCap>
        </unqualifiedPenalty>
        <hardRequirement>False</hardRequirement>
      </li>
    </value>
  </Operation>
  <Operation Class="PatchOperationAddModExtension">
    <xpath>Defs/RecipeDef[defName="MakeAmmo_IronFireLance_RocksPowder"]</xpath>
    <value>
      <li Class="LifeLessons.BillProficiencyExtension">
        <requirements>
          <li>Chemistry</li>
          <li>Labourer</li>
          <li>BasicFabrication</li>
        </requirements>
        <unqualifiedPenalty>
          <qualityCap>Legendary</qualityCap>
        </unqualifiedPenalty>
        <hardRequirement>False</hardRequirement>
      </li>
    </value>
  </Operation>
  <Operation Class="PatchOperationAddModExtension">
    <xpath>Defs/RecipeDef[defName="Make_AF_MusketWeaponPart"]</xpath>
    <value>
      <li Class="LifeLessons.BillProficiencyExtension">
        <requirements>
          <li>Smithing</li>
          <li>BasicFabrication</li>
        </requirements>
        <unqualifiedPenalty>
          <qualityCap>Legendary</qualityCap>
        </unqualifiedPenalty>
        <hardRequirement>False</hardRequirement>
      </li>
    </value>
  </Operation>
  <Operation Class="PatchOperationAddModExtension">
    <xpath>Defs/RecipeDef[defName="Make_AF_PercussionCap"]</xpath>
    <value>
      <li Class="LifeLessons.BillProficiencyExtension">
        <requirements>
          <li>Smithing</li>
          <li>Labourer</li>
          <li>Chemistry</li>
          <li>Geology</li>
        </requirements>
        <unqualifiedPenalty>
          <qualityCap>Legendary</qualityCap>
        </unqualifiedPenalty>
        <hardRequirement>False</hardRequirement>
      </li>
    </value>
  </Operation>
  <Operation Class="PatchOperationAddModExtension">
    <xpath>Defs/RecipeDef[defName="Make_SmallFlintBlock"]</xpath>
    <value>
      <li Class="LifeLessons.BillProficiencyExtension">
        <requirements>
          <li>Geology</li>
          <li>Labourer</li>
        </requirements>
        <unqualifiedPenalty>
          <qualityCap>Legendary</qualityCap>
        </unqualifiedPenalty>
        <hardRequirement>False</hardRequirement>
      </li>
    </value>
  </Operation>
  <Operation Class="PatchOperationAddModExtension">
    <xpath>Defs/RecipeDef[defName="Make_AF_MercuryFulminate"]</xpath>
    <value>
      <li Class="LifeLessons.BillProficiencyExtension">
        <requirements>
          <li>Geology</li>
          <li>Chemistry</li>
          <li>Labourer</li>
        </requirements>
        <unqualifiedPenalty>
          <qualityCap>Legendary</qualityCap>
        </unqualifiedPenalty>
        <hardRequirement>False</hardRequirement>
      </li>
    </value>
  </Operation>
  <Operation Class="PatchOperationAddModExtension">
    <xpath>Defs/RecipeDef[defName="MakeSerpentinePowder"]</xpath>
    <value>
      <li Class="LifeLessons.BillProficiencyExtension">
        <requirements>
          <li>Labourer</li>
          <li>Chemistry</li>
        </requirements>
        <unqualifiedPenalty>
          <qualityCap>Legendary</qualityCap>
        </unqualifiedPenalty>
        <hardRequirement>False</hardRequirement>
      </li>
    </value>
  </Operation>
  <Operation Class="PatchOperationAddModExtension">
    <xpath>Defs/RecipeDef[defName="BuildAF_Gonne"]</xpath>
    <value>
      <li Class="LifeLessons.BillProficiencyExtension">
        <requirements>
          <li>Smithing</li>
          <li>BasicFabrication</li>
        </requirements>
        <unqualifiedPenalty>
          <qualityCap>Poor</qualityCap>
        </unqualifiedPenalty>
        <hardRequirement>False</hardRequirement>
      </li>
    </value>
  </Operation>
  <Operation Class="PatchOperationAddModExtension">
    <xpath>Defs/RecipeDef[defName="BuildAF_IronFireLance"]</xpath>
    <value>
      <li Class="LifeLessons.BillProficiencyExtension">
        <requirements>
          <li>Smithing</li>
          <li>BasicFabrication</li>
        </requirements>
        <unqualifiedPenalty>
          <qualityCap>Poor</qualityCap>
        </unqualifiedPenalty>
        <hardRequirement>False</hardRequirement>
      </li>
    </value>
  </Operation>
  <Operation Class="PatchOperationAddModExtension">
    <xpath>Defs/RecipeDef[defName="BuildAF_FiveGonne"]</xpath>
    <value>
      <li Class="LifeLessons.BillProficiencyExtension">
        <requirements>
          <li>Engineering</li>
          <li>Smithing</li>
        </requirements>
        <unqualifiedPenalty>
          <qualityCap>Poor</qualityCap>
        </unqualifiedPenalty>
        <hardRequirement>False</hardRequirement>
      </li>
    </value>
  </Operation>
  <Operation Class="PatchOperationAddModExtension">
    <xpath>Defs/RecipeDef[defName="BuildGun_AF_Tantsutsu"]</xpath>
    <value>
      <li Class="LifeLessons.BillProficiencyExtension">
        <requirements>
          <li>Smithing</li>
          <li>BasicMathematics</li>
          <li>Artisan</li>
        </requirements>
        <unqualifiedPenalty>
          <qualityCap>Poor</qualityCap>
        </unqualifiedPenalty>
        <hardRequirement>False</hardRequirement>
      </li>
    </value>
  </Operation>
  <Operation Class="PatchOperationAddModExtension">
    <xpath>Defs/RecipeDef[defName="BuildAF_Arquebus"]</xpath>
    <value>
      <li Class="LifeLessons.BillProficiencyExtension">
        <requirements>
          <li>Smithing</li>
          <li>BasicMathematics</li>
        </requirements>
        <unqualifiedPenalty>
          <qualityCap>Poor</qualityCap>
        </unqualifiedPenalty>
        <hardRequirement>False</hardRequirement>
      </li>
    </value>
  </Operation>
  <Operation Class="PatchOperationAddModExtension">
    <xpath>Defs/RecipeDef[defName="BuildAF_Caliver"]</xpath>
    <value>
      <li Class="LifeLessons.BillProficiencyExtension">
        <requirements>
          <li>Smithing</li>
          <li>BasicMathematics</li>
        </requirements>
        <unqualifiedPenalty>
          <qualityCap>Poor</qualityCap>
        </unqualifiedPenalty>
        <hardRequirement>False</hardRequirement>
      </li>
    </value>
  </Operation>
  <Operation Class="PatchOperationAddModExtension">
    <xpath>Defs/RecipeDef[defName="BuildAF_MathclockBlunderbuss"]</xpath>
    <value>
      <li Class="LifeLessons.BillProficiencyExtension">
        <requirements>
          <li>Smithing</li>
          <li>BasicMathematics</li>
        </requirements>
        <unqualifiedPenalty>
          <qualityCap>Poor</qualityCap>
        </unqualifiedPenalty>
        <hardRequirement>False</hardRequirement>
      </li>
    </value>
  </Operation>
  <Operation Class="PatchOperationAddModExtension">
    <xpath>Defs/RecipeDef[defName="BuildAF_Musket"]</xpath>
    <value>
      <li Class="LifeLessons.BillProficiencyExtension">
        <requirements>
          <li>Smithing</li>
          <li>BasicMathematics</li>
        </requirements>
        <unqualifiedPenalty>
          <qualityCap>Poor</qualityCap>
        </unqualifiedPenalty>
        <hardRequirement>False</hardRequirement>
      </li>
    </value>
  </Operation>
  <Operation Class="PatchOperationAddModExtension">
    <xpath>Defs/RecipeDef[defName="BuildAF_Teppo"]</xpath>
    <value>
      <li Class="LifeLessons.BillProficiencyExtension">
        <requirements>
          <li>Smithing</li>
          <li>BasicMathematics</li>
        </requirements>
        <unqualifiedPenalty>
          <qualityCap>Poor</qualityCap>
        </unqualifiedPenalty>
        <hardRequirement>False</hardRequirement>
      </li>
    </value>
  </Operation>
  <Operation Class="PatchOperationAddModExtension">
    <xpath>Defs/RecipeDef[defName="BuildAF_WingedTigerGun"]</xpath>
    <value>
      <li Class="LifeLessons.BillProficiencyExtension">
        <requirements>
          <li>Smithing</li>
          <li>BasicMathematics</li>
        </requirements>
        <unqualifiedPenalty>
          <qualityCap>Poor</qualityCap>
        </unqualifiedPenalty>
        <hardRequirement>False</hardRequirement>
      </li>
    </value>
  </Operation>
  <Operation Class="PatchOperationAddModExtension">
    <xpath>Defs/RecipeDef[defName="BuildGun_AF_MilitaryPistol"]</xpath>
    <value>
      <li Class="LifeLessons.BillProficiencyExtension">
        <requirements>
          <li>Mechanics</li>
          <li>Smithing</li>
          <li>BasicMathematics</li>
        </requirements>
        <unqualifiedPenalty>
          <qualityCap>Poor</qualityCap>
        </unqualifiedPenalty>
        <hardRequirement>False</hardRequirement>
      </li>
    </value>
  </Operation>
  <Operation Class="PatchOperationAddModExtension">
    <xpath>Defs/RecipeDef[defName="BuildGun_AF_Petronel"]</xpath>
    <value>
      <li Class="LifeLessons.BillProficiencyExtension">
        <requirements>
          <li>Smithing</li>
          <li>Mechanics</li>
          <li>BasicMathematics</li>
        </requirements>
        <unqualifiedPenalty>
          <qualityCap>Poor</qualityCap>
        </unqualifiedPenalty>
        <hardRequirement>False</hardRequirement>
      </li>
    </value>
  </Operation>
  <Operation Class="PatchOperationAddModExtension">
    <xpath>Defs/RecipeDef[defName="BuildGun_AF_PocketPistol"]</xpath>
    <value>
      <li Class="LifeLessons.BillProficiencyExtension">
        <requirements>
          <li>Mechanics</li>
          <li>Smithing</li>
          <li>BasicMathematics</li>
        </requirements>
        <unqualifiedPenalty>
          <qualityCap>Poor</qualityCap>
        </unqualifiedPenalty>
        <hardRequirement>False</hardRequirement>
      </li>
    </value>
  </Operation>
  <Operation Class="PatchOperationAddModExtension">
    <xpath>Defs/RecipeDef[defName="BuildGun_AF_PufferPistol"]</xpath>
    <value>
      <li Class="LifeLessons.BillProficiencyExtension">
        <requirements>
          <li>Smithing</li>
          <li>Mechanics</li>
          <li>BasicMathematics</li>
        </requirements>
        <unqualifiedPenalty>
          <qualityCap>Poor</qualityCap>
        </unqualifiedPenalty>
        <hardRequirement>False</hardRequirement>
      </li>
    </value>
  </Operation>
  <Operation Class="PatchOperationAddModExtension">
    <xpath>Defs/RecipeDef[defName="BuildAF_Carbine"]</xpath>
    <value>
      <li Class="LifeLessons.BillProficiencyExtension">
        <requirements>
          <li>Smithing</li>
          <li>Mechanics</li>
          <li>BasicMathematics</li>
        </requirements>
        <unqualifiedPenalty>
          <qualityCap>Poor</qualityCap>
        </unqualifiedPenalty>
        <hardRequirement>False</hardRequirement>
      </li>
    </value>
  </Operation>
  <Operation Class="PatchOperationAddModExtension">
    <xpath>Defs/RecipeDef[defName="BuildAF_WheellockBlunderbuss"]</xpath>
    <value>
      <li Class="LifeLessons.BillProficiencyExtension">
        <requirements>
          <li>Mechanics</li>
          <li>Smithing</li>
          <li>BasicMathematics</li>
        </requirements>
        <unqualifiedPenalty>
          <qualityCap>Poor</qualityCap>
        </unqualifiedPenalty>
        <hardRequirement>False</hardRequirement>
      </li>
    </value>
  </Operation>
  <Operation Class="PatchOperationAddModExtension">
    <xpath>Defs/RecipeDef[defName="Build_AF_WallGun_Crate"]</xpath>
    <value>
      <li Class="LifeLessons.BillProficiencyExtension">
        <requirements>
          <li>Mechanics</li>
          <li>Smithing</li>
          <li>Construction</li>
        </requirements>
        <unqualifiedPenalty>
          <statModifiers>
            <li>
              <stat>GeneralLaborSpeed</stat>
              <applyGlobally>True</applyGlobally>
              <modifier>0.5</modifier>
            </li>
          </statModifiers>
          <qualityCap>Poor</qualityCap>
        </unqualifiedPenalty>
        <hardRequirement>False</hardRequirement>
      </li>
    </value>
  </Operation>
  <Operation Class="PatchOperationAddModExtension">
    <xpath>Defs/RecipeDef[defName="BuildGun_AF_HeavyDragoonPistol"]</xpath>
    <value>
      <li Class="LifeLessons.BillProficiencyExtension">
        <requirements>
          <li>Smithing</li>
          <li>Mechanics</li>
          <li>BasicMathematics</li>
          <li>Geology</li>
        </requirements>
        <unqualifiedPenalty>
          <qualityCap>Poor</qualityCap>
        </unqualifiedPenalty>
        <hardRequirement>False</hardRequirement>
      </li>
    </value>
  </Operation>
  <Operation Class="PatchOperationAddModExtension">
    <xpath>Defs/RecipeDef[defName="BuildGun_AF_LightDragoonPistol"]</xpath>
    <value>
      <li Class="LifeLessons.BillProficiencyExtension">
        <requirements>
          <li>Mechanics</li>
          <li>Smithing</li>
          <li>BasicMathematics</li>
          <li>Geology</li>
        </requirements>
        <unqualifiedPenalty>
          <qualityCap>Poor</qualityCap>
        </unqualifiedPenalty>
        <hardRequirement>False</hardRequirement>
      </li>
    </value>
  </Operation>
  <Operation Class="PatchOperationAddModExtension">
    <xpath>Defs/RecipeDef[defName="BuildGun_AF_HighlandPistol"]</xpath>
    <value>
      <li Class="LifeLessons.BillProficiencyExtension">
        <requirements>
          <li>Smithing</li>
          <li>Mechanics</li>
          <li>BasicMathematics</li>
          <li>Geology</li>
        </requirements>
        <unqualifiedPenalty>
          <qualityCap>Poor</qualityCap>
        </unqualifiedPenalty>
        <hardRequirement>False</hardRequirement>
      </li>
    </value>
  </Operation>
  <Operation Class="PatchOperationAddModExtension">
    <xpath>Defs/RecipeDef[defName="BuildGun_AFQueenAnnePistol"]</xpath>
    <value>
      <li Class="LifeLessons.BillProficiencyExtension">
        <requirements>
          <li>Smithing</li>
          <li>Mechanics</li>
          <li>BasicMathematics</li>
          <li>Geology</li>
        </requirements>
        <unqualifiedPenalty>
          <qualityCap>Poor</qualityCap>
        </unqualifiedPenalty>
        <hardRequirement>False</hardRequirement>
      </li>
    </value>
  </Operation>
  <Operation Class="PatchOperationAddModExtension">
    <xpath>Defs/RecipeDef[defName="BuildGun_AF_SnaphauncePistol"]</xpath>
    <value>
      <li Class="LifeLessons.BillProficiencyExtension">
        <requirements>
          <li>Smithing</li>
          <li>Mechanics</li>
          <li>BasicMathematics</li>
          <li>Geology</li>
        </requirements>
        <unqualifiedPenalty>
          <qualityCap>Poor</qualityCap>
        </unqualifiedPenalty>
        <hardRequirement>False</hardRequirement>
      </li>
    </value>
  </Operation>
  <Operation Class="PatchOperationAddModExtension">
    <xpath>Defs/RecipeDef[defName="BuildAF_FlintlockBlunderbuss"]</xpath>
    <value>
      <li Class="LifeLessons.BillProficiencyExtension">
        <requirements>
          <li>Mechanics</li>
          <li>Smithing</li>
          <li>BasicMathematics</li>
          <li>Geology</li>
        </requirements>
        <unqualifiedPenalty>
          <qualityCap>Poor</qualityCap>
        </unqualifiedPenalty>
        <hardRequirement>False</hardRequirement>
      </li>
    </value>
  </Operation>
  <Operation Class="PatchOperationAddModExtension">
    <xpath>Defs/RecipeDef[defName="BuildAF_FlintlockCarbine"]</xpath>
    <value>
      <li Class="LifeLessons.BillProficiencyExtension">
        <requirements>
          <li>Smithing</li>
          <li>Mechanics</li>
          <li>BasicMathematics</li>
          <li>Geology</li>
        </requirements>
        <unqualifiedPenalty>
          <qualityCap>Poor</qualityCap>
        </unqualifiedPenalty>
        <hardRequirement>False</hardRequirement>
      </li>
    </value>
  </Operation>
  <Operation Class="PatchOperationAddModExtension">
    <xpath>Defs/RecipeDef[defName="BuildAF_FlintlockFusil"]</xpath>
    <value>
      <li Class="LifeLessons.BillProficiencyExtension">
        <requirements>
          <li>Smithing</li>
          <li>Mechanics</li>
          <li>BasicMathematics</li>
          <li>Geology</li>
        </requirements>
        <unqualifiedPenalty>
          <qualityCap>Poor</qualityCap>
        </unqualifiedPenalty>
        <hardRequirement>False</hardRequirement>
      </li>
    </value>
  </Operation>
  <Operation Class="PatchOperationAddModExtension">
    <xpath>Defs/RecipeDef[defName="BuildAF_FowlingPiece"]</xpath>
    <value>
      <li Class="LifeLessons.BillProficiencyExtension">
        <requirements>
          <li>Smithing</li>
          <li>Mechanics</li>
          <li>BasicMathematics</li>
          <li>Geology</li>
        </requirements>
        <unqualifiedPenalty>
          <qualityCap>Poor</qualityCap>
        </unqualifiedPenalty>
        <hardRequirement>False</hardRequirement>
      </li>
    </value>
  </Operation>
  <Operation Class="PatchOperationAddModExtension">
    <xpath>Defs/RecipeDef[defName="BuildAF_FowlingPieceDouble"]</xpath>
    <value>
      <li Class="LifeLessons.BillProficiencyExtension">
        <requirements>
          <li>Mechanics</li>
          <li>Smithing</li>
          <li>BasicMathematics</li>
          <li>Geology</li>
        </requirements>
        <unqualifiedPenalty>
          <qualityCap>Poor</qualityCap>
        </unqualifiedPenalty>
        <hardRequirement>False</hardRequirement>
      </li>
    </value>
  </Operation>
  <Operation Class="PatchOperationAddModExtension">
    <xpath>Defs/RecipeDef[defName="Build_AF_PuckleGun_Crate"]</xpath>
    <value>
      <li Class="LifeLessons.BillProficiencyExtension">
        <requirements>
          <li>Mechanics</li>
          <li>Smithing</li>
          <li>Geology</li>
          <li>Construction</li>
        </requirements>
        <unqualifiedPenalty>
          <statModifiers>
            <li>
              <stat>GeneralLaborSpeed</stat>
              <applyGlobally>True</applyGlobally>
              <modifier>0.5</modifier>
            </li>
          </statModifiers>
          <qualityCap>Poor</qualityCap>
        </unqualifiedPenalty>
        <hardRequirement>False</hardRequirement>
      </li>
    </value>
  </Operation>
  <Operation Class="PatchOperationAddModExtension">
    <xpath>Defs/RecipeDef[defName="BuildAF_BakerRifle"]</xpath>
    <value>
      <li Class="LifeLessons.BillProficiencyExtension">
        <requirements>
          <li>Smithing</li>
          <li>Engineering</li>
          <li>BasicMathematics</li>
          <li>Geology</li>
        </requirements>
        <unqualifiedPenalty>
          <qualityCap>Poor</qualityCap>
        </unqualifiedPenalty>
        <hardRequirement>False</hardRequirement>
      </li>
    </value>
  </Operation>
  <Operation Class="PatchOperationAddModExtension">
    <xpath>Defs/RecipeDef[defName="BuildAF_BreechloadingCarbine"]</xpath>
    <value>
      <li Class="LifeLessons.BillProficiencyExtension">
        <requirements>
          <li>Engineering</li>
          <li>Smithing</li>
          <li>BasicMathematics</li>
          <li>Geology</li>
        </requirements>
        <unqualifiedPenalty>
          <qualityCap>Poor</qualityCap>
        </unqualifiedPenalty>
        <hardRequirement>False</hardRequirement>
      </li>
    </value>
  </Operation>
  <Operation Class="PatchOperationAddModExtension">
    <xpath>Defs/RecipeDef[defName="BuildAF_JagerRifle"]</xpath>
    <value>
      <li Class="LifeLessons.BillProficiencyExtension">
        <requirements>
          <li>Smithing</li>
          <li>Engineering</li>
          <li>BasicMathematics</li>
          <li>Geology</li>
        </requirements>
        <unqualifiedPenalty>
          <qualityCap>Poor</qualityCap>
        </unqualifiedPenalty>
        <hardRequirement>False</hardRequirement>
      </li>
    </value>
  </Operation>
  <Operation Class="PatchOperationAddModExtension">
    <xpath>Defs/RecipeDef[defName="BuildAF_CollierFlintlockRevolverRifle"]</xpath>
    <value>
      <li Class="LifeLessons.BillProficiencyExtension">
        <requirements>
          <li>Smithing</li>
          <li>Engineering</li>
          <li>Mechanics</li>
          <li>BasicMathematics</li>
        </requirements>
        <unqualifiedPenalty>
          <qualityCap>Awful</qualityCap>
        </unqualifiedPenalty>
        <hardRequirement>False</hardRequirement>
      </li>
    </value>
  </Operation>
  <Operation Class="PatchOperationAddModExtension">
    <xpath>Defs/RecipeDef[defName="BuildAF_CollierFlintlockRevolver"]</xpath>
    <value>
      <li Class="LifeLessons.BillProficiencyExtension">
        <requirements>
          <li>Engineering</li>
          <li>Smithing</li>
          <li>BasicMathematics</li>
        </requirements>
        <unqualifiedPenalty>
          <qualityCap>Awful</qualityCap>
        </unqualifiedPenalty>
        <hardRequirement>False</hardRequirement>
      </li>
    </value>
  </Operation>
  <Operation Class="PatchOperationAddModExtension">
    <xpath>Defs/RecipeDef[defName="BuildAF_CollierCaplockRevolverRifle"]</xpath>
    <value>
      <li Class="LifeLessons.BillProficiencyExtension">
        <requirements>
          <li>Smithing</li>
          <li>Engineering</li>
          <li>Mechanics</li>
        </requirements>
        <unqualifiedPenalty>
          <qualityCap>Poor</qualityCap>
        </unqualifiedPenalty>
        <hardRequirement>False</hardRequirement>
      </li>
    </value>
  </Operation>
  <Operation Class="PatchOperationAddModExtension">
    <xpath>Defs/RecipeDef[defName="BuildAF_CollierCaplockRevolver"]</xpath>
    <value>
      <li Class="LifeLessons.BillProficiencyExtension">
        <requirements>
          <li>Smithing</li>
          <li>Engineering</li>
          <li>Mechanics</li>
        </requirements>
        <unqualifiedPenalty>
          <qualityCap>Poor</qualityCap>
        </unqualifiedPenalty>
        <hardRequirement>False</hardRequirement>
      </li>
    </value>
  </Operation>
  <Operation Class="PatchOperationAddModExtension">
    <xpath>Defs/RecipeDef[defName="BuildAF_CollierCaplockRevolverRifle_Conversion"]</xpath>
    <value>
      <li Class="LifeLessons.BillProficiencyExtension">
        <requirements>
          <li>Labourer</li>
          <li>Smithing</li>
        </requirements>
        <unqualifiedPenalty>
          <qualityCap>Poor</qualityCap>
        </unqualifiedPenalty>
        <hardRequirement>False</hardRequirement>
      </li>
    </value>
  </Operation>
  <Operation Class="PatchOperationAddModExtension">
    <xpath>Defs/RecipeDef[defName="BuildAF_CollierCaplockRevolver_Conversion"]</xpath>
    <value>
      <li Class="LifeLessons.BillProficiencyExtension">
        <requirements>
          <li>Labourer</li>
          <li>Smithing</li>
        </requirements>
        <unqualifiedPenalty>
          <qualityCap>Poor</qualityCap>
        </unqualifiedPenalty>
        <hardRequirement>False</hardRequirement>
      </li>
    </value>
  </Operation>
  <Operation Class="PatchOperationAddModExtension">
    <xpath>Defs/RecipeDef[defName="BuildAF_DreyseM1841r"]</xpath>
    <value>
      <li Class="LifeLessons.BillProficiencyExtension">
        <requirements>
          <li>Engineering</li>
          <li>Mechanics</li>
          <li>Smithing</li>
        </requirements>
        <unqualifiedPenalty>
          <qualityCap>Awful</qualityCap>
        </unqualifiedPenalty>
        <hardRequirement>False</hardRequirement>
      </li>
    </value>
  </Operation>
  <Operation Class="PatchOperationAddModExtension">
    <xpath>Defs/RecipeDef[defName="BuildAF_KalthoffRepeater"]</xpath>
    <value>
      <li Class="LifeLessons.BillProficiencyExtension">
        <requirements>
          <li>Engineering</li>
          <li>Smithing</li>
          <li>Mechanics</li>
        </requirements>
        <unqualifiedPenalty>
          <qualityCap>Awful</qualityCap>
        </unqualifiedPenalty>
        <hardRequirement>False</hardRequirement>
      </li>
    </value>
  </Operation>
  <Operation Class="PatchOperationAddModExtension">
    <xpath>Defs/RecipeDef[defName="BuildAF_LorenzonisRepeatingFlintlock"]</xpath>
    <value>
      <li Class="LifeLessons.BillProficiencyExtension">
        <requirements>
          <li>Engineering</li>
          <li>Mechanics</li>
          <li>Smithing</li>
        </requirements>
        <unqualifiedPenalty>
          <qualityCap>Awful</qualityCap>
        </unqualifiedPenalty>
        <hardRequirement>False</hardRequirement>
      </li>
    </value>
  </Operation>
  <Operation Class="PatchOperationAddModExtension">
    <xpath>Defs/RecipeDef[defName="BuildAF_EnfieldRifledMusket"]</xpath>
    <value>
      <li Class="LifeLessons.BillProficiencyExtension">
        <requirements>
          <li>Smithing</li>
          <li>Engineering</li>
          <li>Mechanics</li>
        </requirements>
        <unqualifiedPenalty>
          <qualityCap>Poor</qualityCap>
        </unqualifiedPenalty>
        <hardRequirement>False</hardRequirement>
      </li>
    </value>
  </Operation>
  <Operation Class="PatchOperationAddModExtension">
    <xpath>Defs/RecipeDef[defName="BuildAF_SniderRifle"]</xpath>
    <value>
      <li Class="LifeLessons.BillProficiencyExtension">
        <requirements>
          <li>Smithing</li>
          <li>Engineering</li>
          <li>Mechanics</li>
        </requirements>
        <unqualifiedPenalty>
          <qualityCap>Poor</qualityCap>
        </unqualifiedPenalty>
        <hardRequirement>False</hardRequirement>
      </li>
    </value>
  </Operation>
  <Operation Class="PatchOperationAddModExtension">
    <xpath>Defs/RecipeDef[defName="BuildAF_HallM1819r"]</xpath>
    <value>
      <li Class="LifeLessons.BillProficiencyExtension">
        <requirements>
          <li>Smithing</li>
          <li>Engineering</li>
          <li>Mechanics</li>
        </requirements>
        <unqualifiedPenalty>
          <qualityCap>Poor</qualityCap>
        </unqualifiedPenalty>
        <hardRequirement>False</hardRequirement>
      </li>
    </value>
  </Operation>
  <Operation Class="PatchOperationAddModExtension">
    <xpath>Defs/RecipeDef[defName="BuildAF_RollingBlock"]</xpath>
    <value>
      <li Class="LifeLessons.BillProficiencyExtension">
        <requirements>
          <li>Smithing</li>
          <li>Engineering</li>
        </requirements>
        <unqualifiedPenalty>
          <qualityCap>Poor</qualityCap>
        </unqualifiedPenalty>
        <hardRequirement>False</hardRequirement>
      </li>
    </value>
  </Operation>
  <Operation Class="PatchOperationAddModExtension">
    <xpath>Defs/RecipeDef[defName="BuildAF_Trapdoor"]</xpath>
    <value>
      <li Class="LifeLessons.BillProficiencyExtension">
        <requirements>
          <li>Smithing</li>
          <li>Engineering</li>
          <li>Mechanics</li>
        </requirements>
        <unqualifiedPenalty>
          <qualityCap>Poor</qualityCap>
        </unqualifiedPenalty>
        <hardRequirement>False</hardRequirement>
      </li>
    </value>
  </Operation>
  <Operation Class="PatchOperationAddModExtension">
    <xpath>Defs/RecipeDef[defName="BuildAF_VolcanicRepeatingRifle"]</xpath>
    <value>
      <li Class="LifeLessons.BillProficiencyExtension">
        <requirements>
          <li>Smithing</li>
          <li>Engineering</li>
          <li>Mechanics</li>
        </requirements>
        <unqualifiedPenalty>
          <statModifiers>
            <li>
              <stat>GeneralLaborSpeed</stat>
              <applyGlobally>True</applyGlobally>
              <modifier>0.5</modifier>
            </li>
          </statModifiers>
          <qualityCap>Awful</qualityCap>
        </unqualifiedPenalty>
        <hardRequirement>False</hardRequirement>
      </li>
    </value>
  </Operation>
  <Operation Class="PatchOperationAddModExtension">
    <xpath>Defs/RecipeDef[defName="BuildAF_SpencerM1860r"]</xpath>
    <value>
      <li Class="LifeLessons.BillProficiencyExtension">
        <requirements>
          <li>Smithing</li>
          <li>Engineering</li>
          <li>Mechanics</li>
        </requirements>
        <unqualifiedPenalty>
          <qualityCap>Awful</qualityCap>
        </unqualifiedPenalty>
        <hardRequirement>False</hardRequirement>
      </li>
    </value>
  </Operation>
  <Operation Class="PatchOperationAddModExtension">
    <xpath>Defs/RecipeDef[defName="BuildAF_WinchesterM1873r"]</xpath>
    <value>
      <li Class="LifeLessons.BillProficiencyExtension">
        <requirements>
          <li>Smithing</li>
          <li>Engineering</li>
          <li>Mechanics</li>
        </requirements>
        <unqualifiedPenalty>
          <qualityCap>Awful</qualityCap>
        </unqualifiedPenalty>
        <hardRequirement>False</hardRequirement>
      </li>
    </value>
  </Operation>
</Patch>